{
  "hu": {
    "topbar.discordAdd": "Add to Discord",
    "topbar.support": "Support",
    "topbar.language": "Nyelv",
    "topbar.monthlyGoal": "Havi cél",
    "sidebar.introduction": "Bevezetés",
    "sidebar.commands": "Parancsok",
    "sidebar.settings": "Beállítások",
    "sidebar.policies": "Policies",
    "intro.firstSteps": "Első lépések",
    "commands.registration": "Regisztráció",
    "commands.maps": "Térképek",
    "commands.logging": "Tevékenység naplózás",
    "commands.stats": "Statisztikák",
    "commands.clan": "Klán menedzsment",
    "commands.notifications": "Értesítések",
    "commands.calculators": "Kalkulátorok",
    "commands.settings": "Beállítások",
    "commands.emojis": "Emojis",
    "commands.filter": "Szűrő",
    "settings.appearance": "Megjelenés",
    "settings.language": "Nyelv",
    "settings.system": "Rendszer",
    "settings.dark": "Sötét mód",
    "settings.light": "Világos mód",
    "policies.privacy": "Privacy Policy",
    "policies.terms": "Terms of Service",
    "pages.firstSteps.title": "Első lépések",
    "pages.firstSteps.text": "Itt találod a bot telepítésének, konfigurálásának és első használatának lépéseit.",
    "pages.privacy.title": "Privacy Policy",
    "pages.privacy.text": "A bot csak a működéshez szükséges adatokat kezeli, a felhasználó kérésére törölhetően.",
    "pages.terms.title": "Terms of Service",
    "pages.terms.text": "A szolgáltatás használatával elfogadod a szerver és a bot szabályrendszerét.",
    "content.access": "Hozzáférés",
    "content.optionName": "Option name",
    "content.optionType": "Option type",
    "content.optionValue": "Option value",
    "content.demoImage": "Demó kép"
  },
  "en": { "topbar.discordAdd": "Add to Discord", "topbar.support": "Support", "topbar.language": "Language", "topbar.monthlyGoal": "Monthly goal" },
  "ar": { "topbar.discordAdd": "أضف إلى ديسكورد", "topbar.support": "الدعم", "topbar.language": "اللغة", "topbar.monthlyGoal": "الهدف الشهري" },
  "cs": { "topbar.discordAdd": "Přidat na Discord", "topbar.support": "Podpora", "topbar.language": "Jazyk", "topbar.monthlyGoal": "Měsíční cíl" },
  "nl": { "topbar.discordAdd": "Toevoegen aan Discord", "topbar.support": "Support", "topbar.language": "Taal", "topbar.monthlyGoal": "Maandelijks doel" },
  "fr": { "topbar.discordAdd": "Ajouter à Discord", "topbar.support": "Support", "topbar.language": "Langue", "topbar.monthlyGoal": "Objectif mensuel" },
  "de": { "topbar.discordAdd": "Zu Discord hinzufügen", "topbar.support": "Support", "topbar.language": "Sprache", "topbar.monthlyGoal": "Monatsziel" },
  "el": { "topbar.discordAdd": "Προσθήκη στο Discord", "topbar.support": "Υποστήριξη", "topbar.language": "Γλώσσα", "topbar.monthlyGoal": "Μηνιαίος στόχος" },
  "it": { "topbar.discordAdd": "Aggiungi a Discord", "topbar.support": "Supporto", "topbar.language": "Lingua", "topbar.monthlyGoal": "Obiettivo mensile" },
  "pl": { "topbar.discordAdd": "Dodaj do Discord", "topbar.support": "Wsparcie", "topbar.language": "Język", "topbar.monthlyGoal": "Cel miesięczny" },
  "pt-BR": { "topbar.discordAdd": "Adicionar ao Discord", "topbar.support": "Suporte", "topbar.language": "Idioma", "topbar.monthlyGoal": "Meta mensal" },
  "pt": { "topbar.discordAdd": "Adicionar ao Discord", "topbar.support": "Suporte", "topbar.language": "Idioma", "topbar.monthlyGoal": "Objetivo mensal" },
  "ro": { "topbar.discordAdd": "Adaugă pe Discord", "topbar.support": "Suport", "topbar.language": "Limbă", "topbar.monthlyGoal": "Obiectiv lunar" },
  "sk": { "topbar.discordAdd": "Pridať na Discord", "topbar.support": "Podpora", "topbar.language": "Jazyk", "topbar.monthlyGoal": "Mesačný cieľ" },
  "es": { "topbar.discordAdd": "Agregar a Discord", "topbar.support": "Soporte", "topbar.language": "Idioma", "topbar.monthlyGoal": "Meta mensual" },
  "de-CH": { "topbar.discordAdd": "Zu Discord hinzufügen", "topbar.support": "Support", "topbar.language": "Sprache", "topbar.monthlyGoal": "Monatsziel" },
  "tr": { "topbar.discordAdd": "Discord'a ekle", "topbar.support": "Destek", "topbar.language": "Dil", "topbar.monthlyGoal": "Aylık hedef" }
}
